gardener/__init__.py
gardener/core.py
gardener-2.0.1.dist-info/METADATA
gardener-2.0.1.dist-info/LICENSE
gardener-2.0.1.dist-info/WHEEL
gardener-2.0.1.dist-info/RECORD
